qdscreen/__init__.py
qdscreen/_version.py
qdscreen/compat.py
qdscreen/main.py
qdscreen/py.typed
qdscreen/selector.py
qdscreen/sklearn.py
qdscreen-0.6.4.dist-info/LICENSE
qdscreen-0.6.4.dist-info/METADATA
qdscreen-0.6.4.dist-info/WHEEL
qdscreen-0.6.4.dist-info/top_level.txt
qdscreen-0.6.4.dist-info/RECORD
