Metadata-Version: 2.1
Name: qdscreen
Version: 0.6.4
Summary: Quasi-determinism screening for fast Bayesian Network Structure Learning (from T.Rahier's PhD thesis, 2018)
Home-page: https://github.com/python-qds/qdscreen
Download-URL: https://github.com/python-qds/qdscreen/tarball/0.6.4
Author: Sylvain MARIE <sylvain.marie@se.com>, Thibaud RAHIER <t.rahier@criteo.com>
License: BSD 3-Clause
Keywords: functional dependency correlation categorical feature selection bayesian network structure learning bnsl determinism quasi screening qds qds-bnsl
Classifier: Development Status :: 5 - Production/Stable
Classifier: Intended Audience :: Developers
Classifier: Intended Audience :: Science/Research
Classifier: License :: OSI Approved :: BSD License
Classifier: Topic :: Software Development :: Libraries :: Python Modules
Classifier: Topic :: Scientific/Engineering :: Mathematics
Classifier: Programming Language :: Python
Classifier: Programming Language :: Python :: 2
Classifier: Programming Language :: Python :: 2.7
Classifier: Programming Language :: Python :: 3
Classifier: Programming Language :: Python :: 3.5
Classifier: Programming Language :: Python :: 3.6
Classifier: Programming Language :: Python :: 3.7
Classifier: Programming Language :: Python :: 3.8
Classifier: Programming Language :: Python :: 3.9
License-File: LICENSE
Requires-Dist: numpy (>=1.15)
Requires-Dist: pandas (>=0.21)
Requires-Dist: scipy (>=1.0.1)
Requires-Dist: pyitlib
Requires-Dist: pathlib2 ; python_version < "3.2"
